reversable_primary_key/__init__.py
reversable_primary_key/fields.py
reversable_primary_key/models.py
reversable_primary_key/primary_key.py
reversable_primary_key/serializers.py
django_reversable_primary_key-1.0.7.dist-info/METADATA
django_reversable_primary_key-1.0.7.dist-info/WHEEL
django_reversable_primary_key-1.0.7.dist-info/top_level.txt
django_reversable_primary_key-1.0.7.dist-info/RECORD
