Metadata-Version: 2.1
Name: django-reversable-primary-key
Version: 1.0.7
Summary: Django reversable primary key
Home-page: UNKNOWN
License: MIT
Platform: UNKNOWN
Classifier: Development Status :: 4 - Beta
Classifier: Environment :: Web Environment
Classifier: Intended Audience :: Developers
Classifier: License :: OSI Approved :: MIT License
Classifier: Operating System :: OS Independent
Classifier: Programming Language :: Python :: 3 :: Only
Classifier: Programming Language :: Python :: 3.7
Classifier: Programming Language :: Python :: Implementation :: CPython
Classifier: Topic :: Software Development :: Libraries :: Application Frameworks
Classifier: Topic :: Software Development :: Libraries :: Python Modules
Requires-Python: >=3.6
Requires-Dist: django (>=3.0)
Requires-Dist: samsteady-django-utils (>=1.0.19)
Requires-Dist: samsteady-python-utils (>=1.0.13)
